README.rst
setup.py
odoo_score/__init__.py
odoo_score/__main__.py
odoo_score/api.py
odoo_score/fields.py
odoo_score/migrate.py
odoo_score/models_2.py
odoo_score/models_3.py
odoo_score/models_7.py
odoo_score/odoo_score.py
odoo_score/odoo_score_10.py
odoo_score/odoo_score_11.py
odoo_score/odoo_score_12.py
odoo_score/odoo_score_13.py
odoo_score/odoo_score_14.py
odoo_score/odoo_score_15.py
odoo_score/odoo_score_16.py
odoo_score/odoo_score_17.py
odoo_score/odoo_score_18.py
odoo_score/odoo_score_19.py
odoo_score/odoo_score_6.py
odoo_score/odoo_score_7.py
odoo_score/odoo_score_8.py
odoo_score/odoo_score_9.py
odoo_score/odoo_shell.py
odoo_score/odooctl
odoo_score/secure_db.py
odoo_score/set_workers
odoo_score.egg-info/PKG-INFO
odoo_score.egg-info/SOURCES.txt
odoo_score.egg-info/dependency_links.txt
odoo_score.egg-info/entry_points.txt
odoo_score.egg-info/not-zip-safe
odoo_score.egg-info/requires.txt
odoo_score.egg-info/top_level.txt
odoo_score/scripts/__init__.py
odoo_score/scripts/main.py
odoo_score/scripts/map_module_dependecies.py
odoo_score/scripts/rename_odoo_module.py
odoo_score/scripts/setup.info